vibez/__init__.py
vibez/main.py
vibez-0.1.0.dist-info/licenses/LICENSE
vibez-0.1.0.dist-info/METADATA
vibez-0.1.0.dist-info/WHEEL
vibez-0.1.0.dist-info/entry_points.txt
vibez-0.1.0.dist-info/top_level.txt
vibez-0.1.0.dist-info/RECORD
