Metadata-Version: 2.4
Name: vibez
Version: 0.1.0
Summary: Lightweight CLI tool to extract file contents for LLMs
Home-page: https://github.com/williamgrosset/vibez
License: MIT
Project-URL: Source, https://github.com/williamgrosset/vibez
Project-URL: Bug Tracker, https://github.com/williamgrosset/vibez/issues
Project-URL: Documentation, https://github.com/williamgrosset/vibez#readme
Classifier: Programming Language :: Python :: 3
Classifier: Operating System :: OS Independent
Classifier: Environment :: Console
Classifier: Intended Audience :: Developers
Classifier: Topic :: Software Development :: Code Generators
Classifier: Topic :: Utilities
Requires-Python: >=3.6
License-File: LICENSE
Requires-Dist: pyperclip
Dynamic: classifier
Dynamic: description
Dynamic: description-content-type
Dynamic: home-page
Dynamic: license
Dynamic: license-file
Dynamic: project-url
Dynamic: requires-dist
Dynamic: requires-python
Dynamic: summary
